dup_hawk/__init__.py
dup_hawk/dup_hawk.py
dup_hawk/github.py
dup_hawk-0.0.12.dist-info/LICENSE
dup_hawk-0.0.12.dist-info/METADATA
dup_hawk-0.0.12.dist-info/WHEEL
dup_hawk-0.0.12.dist-info/entry_points.txt
dup_hawk-0.0.12.dist-info/RECORD
