Metadata-Version: 2.1
Name: dup-hawk
Version: 0.0.12
Summary: Python CLI for marking duplicates submissions on GitHub.
Author: PatrickAlphac
Author-email: 54278053+PatrickAlphaC@users.noreply.github.com
Requires-Python: >=3.10,<3.13
Classifier: Programming Language :: Python :: 3
Classifier: Programming Language :: Python :: 3.10
Classifier: Programming Language :: Python :: 3.11
Requires-Dist: click (>=8.1.4,<9.0.0)
Requires-Dist: matplotlib (>=3.7.2,<4.0.0)
Requires-Dist: openai (>=0.27.8,<0.28.0)
Requires-Dist: pandas (>=2.0.3,<3.0.0)
Requires-Dist: plotly (>=5.15.0,<6.0.0)
Requires-Dist: pytest (>=7.4.0,<8.0.0)
Requires-Dist: python-dotenv (>=1.0.0,<2.0.0)
Requires-Dist: requests (>=2.31.0,<3.0.0)
Requires-Dist: scikit-learn (>=1.3.0,<2.0.0)
Requires-Dist: scipy (>=1.11.1,<2.0.0)
